mcp_server/__init__.py
mcp_server/cli.py
mcp_server/metadata.py
mcp_server/server.py
pdfitdown_mcp_server-0.1.0.post1.dist-info/WHEEL
pdfitdown_mcp_server-0.1.0.post1.dist-info/entry_points.txt
pdfitdown_mcp_server-0.1.0.post1.dist-info/METADATA
pdfitdown_mcp_server-0.1.0.post1.dist-info/RECORD
