Metadata-Version: 2.3
Name: pdfitdown-mcp-server
Version: 0.1.0.post1
Summary: MCP Server for PdfItDown
Requires-Dist: fastmcp>=2.14.4
Requires-Dist: pdfitdown[server]
Requires-Python: >=3.10, <3.14
